uup2sksearcher/__init__.py
uup2sksearcher/builder.py
uup2sksearcher/searcher.py
topiksearcher_chromabuilder-1.0.1.dist-info/METADATA
topiksearcher_chromabuilder-1.0.1.dist-info/WHEEL
topiksearcher_chromabuilder-1.0.1.dist-info/top_level.txt
topiksearcher_chromabuilder-1.0.1.dist-info/RECORD
