Metadata-Version: 2.1
Name: topiksearcher-chromabuilder
Version: 1.0.1
Summary: Topik-aware semantic search untuk dokumen hukum berbasis vectorstore, dan pembuatan CrhomaDB dari dokumen humum
Author: Agus Afiantara
Requires-Python: >=3.8
Requires-Dist: langchain
Requires-Dist: langchain-huggingface
Requires-Dist: langchain-chroma
Requires-Dist: rapidfuzz
Requires-Dist: numpy
Requires-Dist: fitz
